setup.py
utility_alpha/__init__.py
utility_alpha/utility_alpha.py
utility_alpha.egg-info/PKG-INFO
utility_alpha.egg-info/SOURCES.txt
utility_alpha.egg-info/dependency_links.txt
utility_alpha.egg-info/not-zip-safe
utility_alpha.egg-info/top_level.txt
utility_alpha/apis/__init__.py
utility_alpha/apis/constants.py
utility_alpha/apis/contracts.py
utility_alpha/apis/metadata.py
utility_alpha/apis/nfts.py
utility_alpha/apis/sfts.py
utility_alpha/apis/tokens.py
utility_alpha/apis/transactions.py
utility_alpha/apis/wallets.py