Metadata-Version: 1.0
Name: utility-alpha
Version: 0.0.1
Summary: Short descript utility alpha
Home-page: UNKNOWN
Author: Dappomatics
Author-email: UNKNOWN
License: UNKNOWN
Platform: UNKNOWN
